eparsecis/__init__.py
eparsecis/elements.py
eparsecis/eparsecis.py
eparsecis/namespace_helpers.py
tests/__init__.py
tests/test_eparsecis.py
tests/data/epcis.xml
tests/data/mdd.xml
tests/data/no-cbv-namespace.xml
eparsecis-4.0.1.dist-info/AUTHORS.rst
eparsecis-4.0.1.dist-info/LICENSE
eparsecis-4.0.1.dist-info/METADATA
eparsecis-4.0.1.dist-info/WHEEL
eparsecis-4.0.1.dist-info/top_level.txt
eparsecis-4.0.1.dist-info/RECORD
