Metadata-Version: 2.1
Name: eparsecis
Version: 4.0.1
Summary: Python lxml parsing for EPCIS Events.
Home-page: https://gitlab.com/serial-lab/eparsecis
Author: Rob Magee
Author-email: slab@serial-lab.com
Maintainer: SerialLab Corp
License: GNU General Public License v3
Keywords: eparsecis
Platform: UNKNOWN
Classifier: Development Status :: 5 - Production/Stable
Classifier: Intended Audience :: Healthcare Industry
Classifier: Intended Audience :: Manufacturing
Classifier: Intended Audience :: Developers
Classifier: License :: OSI Approved :: GNU Affero General Public License v3 or later (AGPLv3+)
Classifier: Natural Language :: English
Classifier: Programming Language :: Python :: 3
Classifier: Programming Language :: Python :: 3.5
Classifier: Programming Language :: Python :: 3.6
Requires-Dist: lxml
Requires-Dist: EPCPyYes
